lilyutils/__init__.py
lilyutils/api.py
lilyutils-0.1.dist-info/DESCRIPTION.rst
lilyutils-0.1.dist-info/METADATA
lilyutils-0.1.dist-info/RECORD
lilyutils-0.1.dist-info/WHEEL
lilyutils-0.1.dist-info/metadata.json
lilyutils-0.1.dist-info/top_level.txt
