Metadata-Version: 2.0
Name: lilyutils
Version: 0.1
Summary: lilyzt utils
Home-page: https://github.com/hxlhxl/lily-utils
Author: hxlhxl
Author-email: huaxiongcool@gmail.com
License: MIT License
Keywords: lily,utils
Platform: any
Classifier: Development Status :: 3 - Alpha
Classifier: Intended Audience :: Developers
Classifier: Topic :: Software Development :: Libraries
Classifier: License :: OSI Approved :: MIT License
Classifier: Programming Language :: Python :: 2
Classifier: Programming Language :: Python :: 2.6
Classifier: Programming Language :: Python :: 2.7
Requires-Dist: requests (==2.17.3)
